{
  "version": 2,
  "store_id": "zimaos-appstore",
  "name": {
    "ca_ES": "Botiga d'aplicacions ZimaOS",
    "cs_CZ": "Obchod s aplikacemi ZimaOS",
    "da_DK": "ZimaOS Appbutik",
    "de_DE": "ZimaOS App Store",
    "el_GR": "Κατάστημα εφαρμογών ZimaOS",
    "en_GB": "ZimaOS App Store",
    "en_US": "ZimaOS AppStore",
    "es_ES": "Tienda de aplicaciones ZimaOS",
    "fr_FR": "Boutique d'applications ZimaOS",
    "ga_IE": "Siopa Aipeanna ZimaOS",
    "hr_HR": "ZimaOS trgovina aplikacija",
    "hu_HU": "ZimaOS alkalmazásbolt",
    "it_IT": "App Store ZimaOS",
    "ja_JP": "ZimaOS アプリストア",
    "ko_KR": "ZimaOS 앱 스토어",
    "ml_IN": "ZimaOS ആപ്പ് സ്റ്റോർ",
    "nb_NO": "ZimaOS appbutikk",
    "nl_NL": "ZimaOS App Store",
    "pl_PL": "Sklep z aplikacjami ZimaOS",
    "pt_BR": "Loja de aplicativos ZimaOS",
    "pt_PT": "Loja de aplicações ZimaOS",
    "ro_RO": "Magazinul de aplicații ZimaOS",
    "ru_RU": "Магазин приложений ZimaOS",
    "sk_SK": "Obchod s aplikáciami ZimaOS",
    "sv_SE": "ZimaOS appbutik",
    "tr_TR": "ZimaOS Uygulama Mağazası",
    "zh_CN": "ZimaOS 应用商店",
    "zh_TW": "ZimaOS 應用商店"
  },
  "description": {
    "ca_ES": "Botiga oficial d'aplicacions de ZimaOS, que ofereix una col·lecció seleccionada d'aplicacions autoallotjades.",
    "cs_CZ": "Oficiální obchod s aplikacemi ZimaOS, který nabízí pečlivě vybranou kolekci self-hosted aplikací.",
    "da_DK": "Den officielle ZimaOS-applikationsbutik med et kurateret udvalg af selvhostede applikationer.",
    "de_DE": "Offizieller ZimaOS App Store mit einer kuratierten Sammlung selbst gehosteter Anwendungen.",
    "el_GR": "Το επίσημο κατάστημα εφαρμογών του ZimaOS, που προσφέρει μια επιμελημένη συλλογή αυτοφιλοξενούμενων εφαρμογών.",
    "en_GB": "Official ZimaOS application store, providing a curated collection of self-hosted applications.",
    "en_US": "Official ZimaOS application store, providing a curated collection of self-hosted applications.",
    "es_ES": "Tienda oficial de aplicaciones de ZimaOS, que ofrece una colección seleccionada de aplicaciones autoalojadas.",
    "fr_FR": "Boutique d'applications officielle de ZimaOS, proposant une sélection d'applications auto-hébergées.",
    "ga_IE": "Siopa oifigiúil feidhmchlár ZimaOS, a sholáthraíonn bailiúchán coimeádta d'fheidhmchláir féin-óstáilte.",
    "hr_HR": "Službena ZimaOS trgovina aplikacija s odabranom kolekcijom samostalno hostanih aplikacija.",
    "hu_HU": "A hivatalos ZimaOS alkalmazásbolt, amely válogatott, saját üzemeltetésű alkalmazásokat kínál.",
    "it_IT": "Store ufficiale delle applicazioni ZimaOS, con una raccolta curata di applicazioni self-hosted.",
    "ja_JP": "公式の ZimaOS アプリケーションストアです。厳選されたセルフホスト型アプリケーションを提供します。",
    "ko_KR": "엄선된 셀프 호스팅 애플리케이션 모음을 제공하는 공식 ZimaOS 애플리케이션 스토어입니다.",
    "ml_IN": "തിരഞ്ഞെടുത്ത സ്വയം-ഹോസ്റ്റഡ് ആപ്ലിക്കേഷനുകളുടെ ശേഖരം നൽകുന്ന ഔദ്യോഗിക ZimaOS ആപ്ലിക്കേഷൻ സ്റ്റോർ.",
    "nb_NO": "Den offisielle ZimaOS-applikasjonsbutikken, med et kuratert utvalg av selvhostede applikasjoner.",
    "nl_NL": "Officiele ZimaOS-applicatiewinkel met een zorgvuldig samengestelde collectie self-hosted applicaties.",
    "pl_PL": "Oficjalny sklep z aplikacjami ZimaOS, oferujący wyselekcjonowaną kolekcję aplikacji self-hosted.",
    "pt_BR": "Loja oficial de aplicativos do ZimaOS, oferecendo uma coleção selecionada de aplicativos auto-hospedados.",
    "pt_PT": "Loja oficial de aplicações do ZimaOS, com uma coleção selecionada de aplicações autoalojadas.",
    "ro_RO": "Magazinul oficial de aplicații ZimaOS, care oferă o colecție atent selectată de aplicații auto-găzduite.",
    "ru_RU": "Официальный магазин приложений ZimaOS с тщательно подобранной коллекцией приложений для самостоятельного размещения.",
    "sk_SK": "Oficiálny obchod s aplikáciami ZimaOS, ktorý ponúka starostlivo vybranú kolekciu self-hosted aplikácií.",
    "sv_SE": "Den officiella ZimaOS-appbutiken med ett kuraterat urval av självhostade applikationer.",
    "tr_TR": "Özenle seçilmiş self-hosted uygulamalar sunan resmi ZimaOS uygulama mağazası.",
    "zh_CN": "ZimaOS 官方应用商店，提供精选的自托管应用集合。",
    "zh_TW": "ZimaOS 官方應用商店，提供精選的自託管應用程式集合。"
  },
  "maintainer": "IceWhaleTech",
  "url": "https://github.com/IceWhaleTech/CasaOS-AppStore"
}
