{
  "id": "node-red",
  "app_id": "org.icewhale.nodered",
  "version": "4.1.10",
  "description": "Node-RED는 다양한 노드를 연결하여 자동화 작업과 애플리케이션을 만들 수 있는 플로우 기반 로우코드 개발 플랫폼입니다. 브라우저 기반 편집기는 사용하기 쉬워 홈 오토메이션, 산업 제어 또는 기타 분야에서 데이터 처리 플로우를 빠르게 구축하려는 사용자에게 이상적입니다.\n\n핵심 기능에는 로우코드 플로우 편집기와 강력한 데이터 처리가 포함됩니다. 이벤트 기반의 논블로킹 모델을 가진 Node.js를 기반으로 구축된 이 플랫폼은 실시간 데이터 수집, 변환 및 시각화를 지원합니다. 5000개 이상의 노드가 있는 팔레트를 통해 사용자는 드래그 앤 드롭으로 플로우를 구성할 수 있습니다. 리치 텍스트 편집기로 JavaScript 함수를 만들어 향상된 커스터마이징이 가능합니다.\n\n플로우를 JSON 형식으로 저장하여 공유를 위한 쉬운 가져오기 및 내보내기를 용이하게 합니다. 내장 라이브러리를 통해 유용한 함수, 템플릿 또는 플로우를 재사용을 위해 저장할 수 있으며, 온라인 플로우 라이브러리는 전 세계적으로 최고의 플로우 공유를 지원합니다. 사용 편의성과 효율성을 핵심으로 하여, 이 플랫폼은 다양한 자동화 요구에 대한 현대적인 솔루션을 제공합니다.\n\n**주요 기능:**\n- 드래그 앤 드롭 노드 연결 기능이 있는 브라우저 기반 로우코드 플로우 편집기\n- 실시간 데이터 수집, 변환 및 시각화\n- Node.js의 이벤트 기반 논블로킹 모델\n- 확장 기능을 위한 5000개 이상의 노드 팔레트\n- JavaScript 함수 생성을 위한 리치 텍스트 편집기\n- 쉬운 공유를 위한 JSON 기반 플로우 저장\n- 함수, 템플릿 및 플로우 저장을 위한 내장 라이브러리\n- 최고의 플로우 공유를 위한 온라인 플로우 라이브러리\n\n**자세히 알아보기:**\n- [Node-RED 공식 웹사이트](https://nodered.org/)\n- [Node-RED GitHub](https://github.com/node-red/node-red)\n",
  "tagline": "이벤트 기반 애플리케이션을 위한 로우코드 프로그래밍",
  "release_notes": "- Node-RED 4.1.10 is a maintenance release.\n- It fixes module name validation for uninstall and tgz install operations.\n- It also ensures project files stay inside the project root path."
}