{
    "version": "2.0",
    "title": "AlbyHub",
    "name": "albyhub",
    "icon": "https://cdn.jsdelivr.net/gh/getAlby/hub@master/frontend/public/icon-512.png",
    "tagline": "Self-custodial Bitcoin Lightning wallet with integrated node and app connections.",
    "overview": "Alby Hub is an open-source, self-custodial Bitcoin Lightning wallet, with the easiest-to-use Lightning Network node for everyone.\nWhether you're an individual, creator, or developer, Alby Hub is your centre for seamless Bitcoin payments.\nEffortlessly connect to a variety of apps like the Alby Browser Extension or Alby Go mobile app, create sub-wallets for family and friends, and take full control of your funds—all within an intuitive interface and developer-ready APIs.\n\n**USEFUL LINKS**\n- [Source Repository](https://github.com/getAlby/hub)\n- [Support](https://support.getalby.com/)\n- [Marketing Site](https://albyhub.com/)\n- [Community of users and developers](https://discord.getalby.com)\n- [Feedback Board, feature requests, bug reports[(https://feedback.getalby.com)\n",
    "thumbnail": "",
    "screenshots": [],
    "category": [
        "Finance"
    ],
    "developer": {
        "name": "",
        "website": "",
        "donate_text": "",
        "donate_link": ""
    },
    "adaptor": {
        "name": "CasaOS Team",
        "website": "https://www.casaos.io",
        "donate_text": "",
        "donate_link": ""
    },
    "support": "",
    "website": "",
    "container": {
        "image": "ghcr.io/getalby/hub:v1.20.0",
        "shell": "bash",
        "privileged": false,
        "network_model": "bridge",
        "web_ui": {
            "http": "",
            "path": ""
        },
        "health_check": "",
        "envs": [],
        "ports": [],
        "volumes": [],
        "devices": [],
        "constraints": {
            "min_memory": 0,
            "min_storage": 0
        },
        "restart_policy": "",
        "sysctls": [],
        "cap_add": [],
        "labels": [],
        "host_name": "",
        "cmd": []
    },
    "abilities": {
        "notification": false,
        "widgets": false,
        "authentication": false,
        "search": false,
        "upnp": false
    },
    "tips": {
        "before_install": []
    },
    "changelog": {
        "latest_updates": "",
        "url": ""
    },
    "latest_update_date": ""
}
