{
  "id": "org.icewhale.archivebox",
  "title": "ArchiveBox",
  "description": "ArchiveBox je snažno, samo-hostano rješenje za arhiviranje interneta koje vam omogućuje stvaranje vlastitog osobnog arhiva web stranica, PDF-ova, videozapisa i više. Funkcionira kao osobni internet arhiv, pohranjujući sadržaj u više formata za dugoročno čuvanje.\n\nSustav se sastoji od više komponenti:\n- **ArchiveBox**: Glavna aplikacija koja pruža web sučelje i mogućnosti arhiviranja\n- **Sonic**: Brz backend za pretraživanje za pretragu cjelokupnog teksta u arhiviranom sadržaju\n- **ArchiveBox Scheduler**: Usluga u pozadini za zakazane zadatke arhiviranja\n- **NoVNC**: Web-based VNC klijent za arhiviranje temeljeno na pregledniku\n\n**Ključne značajke:**\n- Pohranjivanje web stranica u više formata (HTML, PDF, snimke zaslona, itd.)\n- Pretraga cjelokupnog teksta u svom arhiviranom sadržaju\n- Zakazano arhiviranje web stranica i RSS feedova\n- Arhiviranje temeljeno na pregledniku s NoVNC-om\n- Autentifikacija korisnika i kontrola pristupa\n- Ekstrakcija i pohrana medijskih datoteka (videozapisi, audio, PDF-ovi, itd.)\n\n**Saznajte više:**\n- [Službena web stranica ArchiveBox](https://archivebox.io)\n- [ArchiveBox GitHub Repozitorij](https://github.com/ArchiveBox/ArchiveBox)\n- [ArchiveBox Dokumentacija](https://github.com/ArchiveBox/ArchiveBox/wiki)\n",
  "tagline": "Samo-hostano rješenje za arhiviranje interneta",
  "release_note": "- v0.7.4 refreshes Docker container dependencies and 0.7.x package metadata/lockfiles.\n- Chromium, Node.js, gosu, yt-dlp, single-file, curl, wget, git, ripgrep, ffmpeg, and Python dependencies were updated.\n- Back up archives before upgrading and run archivebox version after the update.",
  "tips": {
    "before_install": "**Zadani Račun**\n\n| Korisničko ime | Lozinka |\n|----------------|---------|\n| `casaos`       | `casaos` |\n"
  }
}