{
  "id": "langflow",
  "app_id": "org.icewhale.langflow",
  "title": "Langflow",
  "tagline": "Interfaccia open-source per la creazione e il debug di applicazioni multi-agente e RAG",
  "description": "Langflow è una potente interfaccia utente open-source progettata specificamente per la creazione e il debug di applicazioni multi-agente e di Retrieval-Augmented Generation (RAG). Fornisce un'interfaccia visuale drag-and-drop che semplifica il processo di creazione di flussi di lavoro AI complessi.\n\nIl sistema è composto da due componenti principali:\n- **Langflow**: L'applicazione principale che fornisce un'interfaccia visuale per la creazione di flussi di lavoro AI\n- **PostgreSQL**: Un robusto sistema di database per la memorizzazione di dati e configurazioni dell'applicazione\n\n**Caratteristiche principali:**\n- Interfaccia visuale drag-and-drop per la creazione di flussi di lavoro AI\n- Supporto per sistemi multi-agente e applicazioni RAG\n- Strumenti di debug integrati per test e ottimizzazione\n- Archiviazione persistente per flussi di lavoro e configurazioni\n- Distribuzione facile con container Docker\n\n**Per saperne di più:**\n- [Sito web ufficiale di Langflow](https://www.langflow.org)\n- [Repository GitHub di Langflow](https://github.com/langflow-ai/langflow)\n- [Documentazione](https://docs.langflow.org)\n",
  "release_notes": "- v1.9.3 is a critical security release with SSRF protection, DNS rebinding prevention, and CVE-related dependency fixes.\n- The release adds Python 3.14 support and fixes provider/model UI behavior including model toggle stability and Agent dropdown refresh.\n- The langflowai/langflow:1.9.3 Docker image tag was published on 2026-05-15."
}