{
  "id": "nzbget",
  "app_id": "org.icewhale.nzbget",
  "tagline": "Downloader Usenet efficiente",
  "description": "NZBGet può essere eseguito su quasi qualsiasi dispositivo - PC classico, NAS, lettore multimediale, ricevitore SAT, router WLAN, ecc. La zona download fornisce binari precompilati per Windows, macOS, Linux (compatibile con molte CPU e varianti di piattaforma), FreeBSD e Android. Per altre piattaforme, il programma può essere compilato dalle fonti.",
  "release_notes": "- NZBGet 26.1 improves archived NZB handling support.\n- Adds NzbDirArchiveScan for scanning zip, rar, 7z, and other archives in NzbDir.\n- Uses the LinuxServer 26.1.20260522 image build for this release line."
}