{
  "id": "org.icewhale.actualbudget",
  "tagline": "프라이버시 우선 재정 관리 앱, 봉투 예산 및 다중 기기 동기화 지원.",
  "release_note": "- v26.5.2 is functionally identical to v26.5.1 and was published to resolve Windows Store release packaging.\n- It fixes authentication rate limiting, desktop self-signed certificates, and UUID generation in insecure HTTP contexts.",
  "description": "Actual Budget은 로컬 우선 봉투 예산을 사용하는 빠르고 프라이버시 중심의 재정 관리 앱으로, 데이터에 대한 완전한 제어를 보장합니다. 직관적인 인터페이스는 오프라인 사용을 지원하며, 멀티 디바이스 동기화와 선택적 종단 간 암호화를 통해 안전하고 효율적인 재정 관리 경험을 제공하여, 명확한 재정 감독을 원하는 사용자에게 이상적입니다.\n\n앱의 핵심 기능에는 실제 소득을 기반으로 한 봉투 예산, 빠른 거래 처리, 직관적인 재정 보고가 포함됩니다. 지출을 추적하고 월간 저축을 명확하게 모니터링하는 데 도움이 되며, 빠른 분류, 분할 거래, 이체를 위한 간소화된 거래 편집기를 제공합니다. 내장된 순자산 및 현금 흐름 보고서는 재정 통찰력을 제공하고, 사용자 정의 보고서 엔진을 통해 특정 요구 사항에 맞춘 보고서를 작성할 수 있습니다. 실행 취소 및 다시 실행 기능을 통해 사용자는 쉽게 실수를 수정할 수 있어 운영 유연성을 유지합니다.\n\ngoCardless (EU/UK) 또는 SimpleFIN (US/Canada)을 통해 은행 계좌를 통합하고, 데이터 프라이버시를 위한 멀티 디바이스 동기화를 지원하며, YNAB4, nYNAB 및 QIF, OFX, QFX, CAMT.053, CSV 파일에서 거래 데이터 가져오기를 가능하게 하여 기존 재정 기록의 마이그레이션을 단순화합니다. 커뮤니티 문서가 사용성을 향상시키고, 앱의 간단한 운영과 높은 유연성이 현대적인 재정 관리 솔루션을 제공합니다.\n\n**주요 기능:**\n- 프라이버시 중심 개인 재정 관리\n- 봉투 예산 방법론\n- 멀티 디바이스 동기화\n- 종단 간 암호화 지원\n- 로컬 데이터 소유권\n- 빠르고 반응성 있는 인터페이스\n- 오픈 소스 및 자체 호스팅\n- 은행 계좌 동기화\n- 상세한 재정 보고\n- 예산 추적 및 분석\n\n**더 알아보기:**\n- [Actual Budget 공식 웹사이트](https://actualbudget.org)\n- [Actual Budget GitHub 저장소](https://github.com/actualbudget/actual)\n- [Actual Budget Docker 이미지](https://hub.docker.com/r/actualbudget/actual-server)\n",
  "tips": {
    "before_install": "처음으로 웹 페이지를 열면 오류 팝업이 표시됩니다. `Advanced options` 옵션을 클릭하여 Actual Budget 웹 페이지에 정상적으로 액세스합니다.\n"
  }
}